iamscan/__init__.py
iamscan/__main__.py
iamscan/commands.py
iamscan/policy.py
tests/__init__.py
tests/test_code.py
tests/validations.py
iamscan-0.0.1.dist-info/LICENSE
iamscan-0.0.1.dist-info/METADATA
iamscan-0.0.1.dist-info/WHEEL
iamscan-0.0.1.dist-info/entry_points.txt
iamscan-0.0.1.dist-info/top_level.txt
iamscan-0.0.1.dist-info/RECORD
