Metadata-Version: 2.1
Name: iamscan
Version: 0.0.1
Summary: Checks code for needed AWS IAM Privileges
Home-page: UNKNOWN
Author: David Zajac
Author-email: davidzajac321@gmail.com
License: UNKNOWN
Keywords: aws,python,bash,aws-cli,iam
Platform: UNKNOWN
Classifier: Development Status :: 1 - Planning
Classifier: Intended Audience :: Developers
Classifier: Programming Language :: Python :: 3
Classifier: Operating System :: Unix
Classifier: Operating System :: MacOS :: MacOS X
Classifier: Operating System :: Microsoft :: Windows
Requires-Dist: PyYAML (>=5)
